LICENSE.txt
MANIFEST.in
README.md
requirements.txt
setup.cfg
setup.py
patchworkdocker/__init__.py
patchworkdocker/cli.py
patchworkdocker/core.py
patchworkdocker/docker_images.py
patchworkdocker/errors.py
patchworkdocker/importers.py
patchworkdocker/meta.py
patchworkdocker/modifiers.py
patchworkdocker.egg-info/PKG-INFO
patchworkdocker.egg-info/SOURCES.txt
patchworkdocker.egg-info/dependency_links.txt
patchworkdocker.egg-info/entry_points.txt
patchworkdocker.egg-info/requires.txt
patchworkdocker.egg-info/top_level.txt
patchworkdocker.egg-info/zip-safe
patchworkdocker/_external/__init__.py
patchworkdocker/_external/key_value_string_parser.py
patchworkdocker/_external/verbosity_argument_parser.py
subrepos/colin-nolan/key_value_string_parser.py/.gitrepo
subrepos/colin-nolan/key_value_string_parser.py/key_value_string_parser.py
subrepos/colin-nolan/verbosity-argument-parser.py/.gitrepo
subrepos/colin-nolan/verbosity-argument-parser.py/verbosity-argument-parser.py