Metadata-Version: 2.1
Name: patchworkdocker
Version: 0.0.0
Summary: TODO
Home-page: https://github.com/wtsi-hgi/patchwork-docker
Author: Colin Nolan
Author-email: cn580@alumni.york.ac.uk
License: MIT
Platform: UNKNOWN
